flask_font_awesome/__init__.py
flask_font_awesome/static/js/all.min.js
flask_font_awesome/templates/font_awesome.html
font_awesome_flask-0.1.5.dist-info/LICENSE
font_awesome_flask-0.1.5.dist-info/WHEEL
font_awesome_flask-0.1.5.dist-info/METADATA
font_awesome_flask-0.1.5.dist-info/RECORD
