Metadata-Version: 2.1
Name: Font-Awesome-Flask
Version: 0.1.5
Summary: Font-Awesome-Flask is an extension for Flask that adds support for Font Awesome to your web application.
Keywords: flask,extension,font awesome
Author-email: Steven van de Graaf <steven@vandegraaf.xyz>
Requires-Python: ~=3.8
Classifier: Development Status :: 4 - Beta
Classifier: Environment :: Web Environment
Classifier: Framework :: Flask
Classifier: Intended Audience :: Developers
Classifier: License :: OSI Approved :: GNU General Public License v3 or later (GPLv3+)
Classifier: Operating System :: OS Independent
Classifier: Programming Language :: Python
Classifier: Programming Language :: Python :: 3
Classifier: Programming Language :: Python :: 3.8
Classifier: Programming Language :: Python :: 3.9
Classifier: Programming Language :: Python :: 3.10
Classifier: Programming Language :: Python :: 3.11
Classifier: Topic :: Internet :: WWW/HTTP :: Dynamic Content
Classifier: Topic :: Software Development :: Libraries :: Python Modules
Requires-Dist: importlib-resources; python_version < '3.10'
Requires-Dist: flask
Requires-Dist: markupsafe
Requires-Dist: autoflake ; extra == "dev"
Requires-Dist: black ; extra == "dev"
Requires-Dist: flake8 ; extra == "dev"
Requires-Dist: isort ; extra == "dev"
Requires-Dist: mypy ; extra == "dev"
Requires-Dist: pre-commit ; extra == "dev"
Requires-Dist: pyupgrade ; extra == "dev"
Requires-Dist: furo ; extra == "docs"
Requires-Dist: myst-parser ; extra == "docs"
Requires-Dist: sphinx ; extra == "docs"
Requires-Dist: sphinx-copybutton ; extra == "docs"
Requires-Dist: sphinxext-opengraph ; extra == "docs"
Project-URL: Home, https://github.com/sgraaf/font-awesome-flask
Project-URL: Issues, https://github.com/sgraaf/font-awesome-flask/issues
Project-URL: Source code, https://github.com/sgraaf/font-awesome-flask
Provides-Extra: dev
Provides-Extra: docs
